{
  "ID" : "grass_block",
  "blockID": 1,
  "dontOccludeSameBlock" : false,
  "faces" : {
    "east" : {
      "textureID" : "grass_block_side",
      "vertices" : [
        [1, 1, 0,  0, 0,  1, 1, 1, 1],
        [1, 0, 0,  0, 1,  1, 1, 1, 1],
        [1, 0, 1,  1, 1,  1, 1, 1, 1],
        [1, 1, 1,  1, 0,  1, 1, 1, 1]
      ]
    },
    "west" : {
      "textureID" : "grass_block_side",
      "vertices" : [
        [0, 1, 1,  0, 0,  1, 1, 1, 1],
        [0, 0, 1,  0, 1,  1, 1, 1, 1],
        [0, 0, 0,  1, 1,  1, 1, 1, 1],
        [0, 1, 0,  1, 0,  1, 1, 1, 1]
      ]
    },
    "up" : {
      "textureID" : "grass_block_top",
      "vertices" : [
        [0, 1, 1,  0, 0,  0.55, 0.75, 0.3, 1],
        [0, 1, 0,  0, 1,  0.55, 0.75, 0.3, 1],
        [1, 1, 0,  1, 1,  0.55, 0.75, 0.3, 1],
        [1, 1, 1,  1, 0,  0.55, 0.75, 0.3, 1]
      ]
    },
    "down" : {
      "textureID" : "dirt",
      "vertices" : [
        [0, 0, 0,  0, 0,  1, 1, 1, 1],
        [0, 0, 1,  0, 1,  1, 1, 1, 1],
        [1, 0, 1,  1, 1,  1, 1, 1, 1],
        [1, 0, 0,  1, 0,  1, 1, 1, 1]
      ]
    },
    "north" : {
      "textureID" : "grass_block_side",
      "vertices" : [
        [1, 1, 1,  0, 0,  1, 1, 1, 1],
        [1, 0, 1,  0, 1,  1, 1, 1, 1],
        [0, 0, 1,  1, 1,  1, 1, 1, 1],
        [0, 1, 1,  1, 0,  1, 1, 1, 1]
      ]
    },
    "south" : {
      "textureID" : "grass_block_side",
      "vertices" : [
        [1, 1, 1,  0, 0,  1, 1, 1, 1],
        [1, 0, 1,  0, 1,  1, 1, 1, 1],
        [0, 0, 1,  1, 1,  1, 1, 1, 1],
        [0, 1, 1,  1, 0,  1, 1, 1, 1]
      ]
    },
    "east_overlay" : {
      "textureID" : "grass_block_side_overlay",
      "vertices" : [
        [1, 1, 1,  0, 0,  1, 1, 1, 1],
        [1, 0, 1,  0, 1,  1, 1, 1, 1],
        [0, 0, 1,  1, 1,  1, 1, 1, 1],
        [0, 1, 1,  1, 0,  1, 1, 1, 1]
      ]
    },
    "west_overlay" : {
      "textureID" : "grass_block_side_overlay",
      "vertices" : [
        [0, 1, 1,  0, 0,  0.55, 0.75, 0.3, 1],
        [0, 0, 1,  0, 1,  0.55, 0.75, 0.3, 1],
        [0, 0, 0,  1, 1,  0.55, 0.75, 0.3, 1],
        [0, 1, 0,  1, 0,  0.55, 0.75, 0.3, 1]
      ]
    },
    "north_overlay" : {
      "textureID" : "grass_block_side_overlay",
      "vertices" : [
        [1, 1, 1,  0, 0,  0.55, 0.75, 0.3, 1],
        [1, 0, 1,  0, 1,  0.55, 0.75, 0.3, 1],
        [0, 0, 1,  1, 1,  0.55, 0.75, 0.3, 1],
        [0, 1, 1,  1, 0,  0.55, 0.75, 0.3, 1]
      ]
    },
    "south_overlay" : {
      "textureID" : "grass_block_side_overlay",
      "vertices" : [
        [0, 1, 0,  0, 0,  0.55, 0.75, 0.3, 1],
        [0, 0, 0,  0, 1,  0.55, 0.75, 0.3, 1],
        [1, 0, 0,  1, 1,  0.55, 0.75, 0.3, 1],
        [1, 1, 0,  1, 0,  0.55, 0.75, 0.3, 1]
      ]
    }
  }
}
